<dialogue>
  <info box="right">
  <portrait_r entry="player" eye="surprised" mouth="yell">
  <male>
    <sjis>
      どうしたんだよ<end_line>
      <partner>！<end_line>
      大丈夫か？<end_line>
    </sjis>
  </male>
  <female>
    <sjis>
      どうしたのよ<end_line>
      <partner>！<end_line>
      大丈夫？<end_line>
    </sjis>
  </female>
  <ascii>
    <partner>,<end_line>
    what's wrong!?<end_line>
  </ascii>
</dialogue>
<dialogue>
  <partner name="run-dor">
  <info box="left">
  <portrait_l entry="partner" eye="sad" mouth="serious">
  <portrait_r entry="player" eye="surprised" mouth="yell">
  <sjis>
    コノ奥カラ　強力ナえねるぎーヲ<end_line>
    検知シテイマス<three_dots><end_line>
    気ヲツケテ下サイ<end_line>
  </sjis>
  <ascii>
    I Detect A Strong Energy<end_line>
    Coming From Inside<three_dots><end_line>
    Please Be Careful.<end_line>
  </ascii>
</dialogue>
<dialogue>
  <partner name="enzi">
  <info box="left">
  <portrait_l entry="partner" eye="sad" mouth="serious">
  <portrait_r entry="player" eye="surprised" mouth="yell">
  <sjis>
    なんじゃ、この気の量は<three_dots><end_line>
    この奥には何かあるぞ<end_line>
    気をつけるのじゃぞ<three_dots><end_line>
  </sjis>
  <ascii>
    What is this mass of feelings<three_dots><end_line>
    There's something inside.<end_line>
    Be careful.<end_line>
  </ascii>
</dialogue>
<dialogue>
  <partner name="killfith">
  <info box="left">
  <portrait_l entry="partner" eye="sad" mouth="serious">
  <portrait_r entry="player" eye="surprised" mouth="yell">
  <sjis>
    なんてイヤなフンイキだ<three_dots><end_line>
    この奥には何かあるぞ<end_line>
    覚悟しておけ<three_dots><end_line>
  </sjis>
  <ascii>
    This disgusting feeling again<three_dots><end_line>
    There's something inside.<end_line>
    Be prepared<three_dots><end_line>
  </ascii>
</dialogue>
<dialogue>
  <partner name="rufeel">
  <info box="left">
  <portrait_l entry="partner" eye="sad" mouth="serious">
  <portrait_r entry="player" eye="surprised" mouth="yell">
  <sjis>
    うぅ<three_dots>、この感じ<three_dots><end_line>
    この奥には絶対何かありますわ<end_line>
    気をつけてください<end_line>
  </sjis>
  <ascii>
    Uu<three_dots> this feeling<three_dots><end_line>
    There must be something inside.<end_line>
    Please be careful.<end_line>
  </ascii>
</dialogue>
<dialogue>
  <info box="right">
  <portrait_l entry="partner" eye="sad" mouth="serious">
  <portrait_r entry="player" eye="decided" mouth="serious">
  <male>
    <sjis>
      お、おう<three_dots><end_line>
      わかった！<end_line>
    </sjis>
  </male>
  <female>
    <sjis>
      う、うん<three_dots><end_line>
      わかった！<end_line>
    </sjis>
  </female>
  <ascii>
    Y-yeah<three_dots><end_line>
    I will!<end_line>
  </ascii>
</dialogue>
