<dialogue>
  <partner name="run-dor">
  <info box="simple">
  <portrait_l name="partner">
  <sjis>
    ダカラ　私ハ<three_dots><end_line>
    みゅーの様ヲ　守ルタメ<three_dots>！<end_line>
  </sjis>
  <ascii>
    I Have Already Informed You<three_dots><end_line>
    I Must Protect Lady Murno<three_dots><end_line>
  </ascii>
</dialogue>
<dialogue>
  <partner name="enzi">
  <info box="simple">
  <portrait_l name="partner">
  <sjis>
    はなさんか！<end_line>
    ワガハイはミューノの様子を<three_dots><end_line>
  </sjis>
  <ascii>
    Let me go!<end_line>
    I must check on Murno<three_dots><end_line>
  </ascii>
</dialogue>
<dialogue>
  <partner name="killfith">
  <info box="simple">
  <portrait_l name="partner">
  <sjis>
    はなせ！<end_line>
    私はあいさつになど<three_dots><end_line>
  </sjis>
  <ascii>
    Release me!<end_line>
    I don't need to see the Chief<three_dots><end_line>
  </ascii>
</dialogue>
<dialogue>
  <partner name="rufeel">
  <info box="simple">
  <portrait_l name="partner">
  <sjis>
    あの<three_dots>ちょっと<three_dots>！<end_line>
    私、ミューノ様に相談が<three_dots><end_line>
  </sjis>
  <ascii>
    Um<three_dots>Please let go<three_dots>！<end_line>
    I want to ask Lady Murno something<three_dots><end_line>
  </ascii>
</dialogue>
<dialogue>
  <info box="simple">
  <portrait_l name="vee">
  <sjis>
    あー！<end_line>
    それはわかったから<end_line>
  </sjis>
  <ascii>
    Yeah~!<end_line>
    I totally understand that.<end_line>
  </ascii>
</dialogue>
<dialogue>
  <info box="left">
  <portrait_l entry="player" eye="serious" mouth="tense">
  <sjis>
    あ、親方<end_line>
    <partner>も<end_line>
  </sjis>
  <ascii>
    Oh, it's Master and <partner>.<end_line>
  </ascii>
</dialogue>
<dialogue>
  <info box="right">
  <portrait_l entry="player" eye="serious" mouth="tense">
  <portrait_r entry="vee" eye="serious" mouth="serious">
  <sjis>
    もしかして<three_dots><end_line>
    アンタもミューノのところに<end_line>
    行くつもりだった？<end_line>
  </sjis>
  <ascii>
    So<three_dots><end_line>
    You were planning to<end_line>
    go see Murno too, eh?<end_line>
  </ascii>
</dialogue>
<dialogue>
  <partner name="killfith">
  <info box="left">
  <portrait_l entry="partner" eye="surprised" mouth="tense">
  <sjis>
    な<three_dots>！<end_line>
    こいつは知らんが<end_line>
    私はミューノのところへなど<three_dots><end_line>
  </sjis>
  <ascii>
    Wha<three_dots>?<end_line>
    I don't know about them,<end_line>
    but I had no such plans.<end_line>
  </ascii>
</dialogue>
<dialogue>
  <info box="left">
  <portrait_l entry="player" eye="serious" mouth="tense">
  <male>
    <sjis>
      オレは<three_dots><end_line>
    </sjis>
  </male>
  <female>
    <sjis>
      わたしは<three_dots><end_line>
    </sjis>
  </female>
  <ascii>
    I<three_dots><end_line>
  </ascii>
</dialogue>
<choice>
  <info box="left">
  <portrait_l entry="player" eye="serious" mouth="tense">
  <option>
    <sjis>
      ミューノのところに行くつもりだった<end_line>
    </sjis>
    <ascii>
      I was planning to see Murno.<end_line>
    </ascii>
  </option>
  <option>
    <sjis>
      そんな気さらさらありません<end_line>
    </sjis>
    <ascii>
      Nah, not really.<end_line>
    </ascii>
  </option>
</choice>
<dialogue>
  <info box="left">
  <portrait_l entry="player" eye="serious" mouth="neutral">
  <male>
    <sjis>
      みんな帰ってこないし<end_line>
      なにやってンのかなって<three_dots><end_line>
    </sjis>
  </male>
  <female>
    <sjis>
      みんな帰ってこないし<end_line>
      なにやってるのかなって<three_dots><end_line>
    </sjis>
  </female>
  <ascii>
    You were taking a while, so I was<end_line>
    wondering what you were doing<three_dots><end_line>
  </ascii>
</dialogue>
<dialogue>
  <info box="right">
  <portrait_l entry="player" eye="serious" mouth="neutral">
  <portrait_r name="player">
  <sjis>
    なるほど、つまり<end_line>
    ミューノのことが心配だったと！<end_line>
    へ～<three_dots>、そ～なんだ～<three_dots><end_line>
  </sjis>
  <ascii>
    I see, so in other words,<end_line>
    you were worried about Murno!<end_line>
    Hehe~<three_dots>I see~<three_dots><end_line>
  </ascii>
</dialogue>
<dialogue>
  <info box="nobox">
  <portrait_l entry="player" eye="serious" mouth="neutral">
  <sjis>
    用意できたから<end_line>
    玄関で待ってようかなって<end_line>
    思っただけで<three_dots><end_line>
  </sjis>
  <ascii>
    I was just thinking about<end_line>
    waiting in the entrance<end_line>
    once I was ready<three_dots><end_line>
  </ascii>
</dialogue>
<dialogue>
  <info box="right">
  <portrait_l entry="player" eye="serious" mouth="neutral">
  <portrait_r name="player">
  <sjis>
    はいはい<end_line>
    そういうことにしといてあげるよ<end_line>
    アタシってばやさしいだろ？<end_line>
  </sjis>
  <ascii>
    Ah, yes, yes.<end_line>
    I'll leave it at that then.<end_line>
    I'm so nice, aren't I?<end_line>
  </ascii>
</dialogue>
<dialogue>
  <info box="left">
  <portrait_l entry="player" eye="surprised" mouth="stressed">
  <male>
    <sjis>
      な、なんだよ！<end_line>
      オレは別に<three_dots>！<end_line>
    </sjis>
  </male>
  <female>
    <sjis>
      な、なによ！<end_line>
      わたしは別に<three_dots>！<end_line>
    </sjis>
  </female>
  <ascii>
    W-What?!<end_line>
    I wasn't<three_dots>!<end_line>
  </ascii>
</dialogue>
<dialogue>
  <info box="right">
  <portrait_l entry="player" eye="surprised" mouth="stressed">
  <portrait_r name="vee">
  <sjis>
    まあまあ<end_line>
    アンタたちには悪いけど<end_line>
    お姫さまはまだユメの中だよ<end_line>
  </sjis>
  <ascii>
    Now, now.<end_line>
    I feel sorry for you guys, but<end_line>
    your princess is still dreaming.<end_line>
  </ascii>
</dialogue>
<dialogue>
  <info box="right">
  <portrait_l entry="player" eye="surprised" mouth="stressed">
  <portrait_r name="vee">
  <sjis>
    よっぽど疲れてたんだろうね<end_line>
    もう少し寝かしといてやんな<end_line>
  </sjis>
  <ascii>
    She must be really tired.<end_line>
    Let her rest a bit longer.<end_line>
  </ascii>
</dialogue>
<dialogue>
  <info box="left">
  <portrait_l entry="player" eye="serious" mouth="neutral">
  <sjis>
    そっか<end_line>
    わかった<end_line>
  </sjis>
  <ascii>
    Oh, I see.<end_line>
    Alright then.<end_line>
  </ascii>
</dialogue>
<dialogue>
  <partner name="run-dor">
  <info box="left">
  <portrait_l entry="partner" eye="serious" mouth="neutral">
  <sjis>
    私ハ　みゅーの様ガ　起キルマデ<end_line>
    部屋デ　護衛ニアタリマス<end_line>
  </sjis>
  <ascii>
    I Will Stand Guard<end_line>
    Until She Awakens.<end_line>
  </ascii>
</dialogue>
<dialogue>
  <partner name="enzi">
  <info box="left">
  <portrait_l entry="partner" eye="serious" mouth="serious">
  <sjis>
    ミューノがまだ寝ているのなら<end_line>
    ワガハイは部屋で護衛を<three_dots><end_line>
  </sjis>
  <ascii>
    Then I'll stand guard in her room<three_dots><end_line>
  </ascii>
</dialogue>
<dialogue>
  <partner name="killfith">
  <info box="left">
  <portrait_l entry="partner" eye="serious" mouth="talk">
  <sjis>
    ならば私も<end_line>
    もう少し寝ると<three_dots><end_line>
  </sjis>
  <ascii>
    In that case,<end_line>
    I'm going back to sleep too<three_dots><end_line>
  </ascii>
</dialogue>
<dialogue>
  <partner name="rufeel">
  <info box="left">
  <portrait_l entry="partner" eye="serious" mouth="neutral">
  <sjis>
    ミューノ様がまだ寝ているのなら<end_line>
    私は部屋で護衛を<three_dots><end_line>
  </sjis>
  <ascii>
    Awake or not,<end_line>
    my duty is to protect her<three_dots><end_line>
  </ascii>
</dialogue>
<dialogue>
  <info box="right">
  <portrait_l entry="partner" eye="serious" mouth="neutral">
  <portrait_r name="player">
  <sjis>
    だ～か～ら！<end_line>
    そんなことしてるヒマがあったら<end_line>
    修行の続きだって言ってるだろ！？<end_line>
  </sjis>
  <ascii>
    I told you!<end_line>
    If you've got so much free time,<end_line>
    then you should use it for training!<end_line>
  </ascii>
</dialogue>
<dialogue>
  <info box="left">
  <portrait_l entry="player" eye="surprised" mouth="tense">
  <sjis>	
    今から！？<end_line>
  </sjis>
  <ascii>
    Right now!?<end_line>
  </ascii>
</dialogue>
<dialogue>
  <info box="right">
  <portrait_l entry="player" eye="surprised" mouth="tense">
  <portrait_r name="player">
  <sjis>
    アンタもそんなこと言うか！？<end_line>
    この親方不幸弟子！<end_line>
  </sjis>
  <ascii>
    You're saying that too?!<end_line>
    Some apprentice you are!<end_line>
  </ascii>
</dialogue>
<dialogue>
  <info box="right">
  <portrait_l entry="player" eye="sad" mouth="tense">
  <portrait_r name="player">
  <sjis>
    はやく修理の仕事ができるくらい<end_line>
    使い物になってもらわないと<end_line>
    ホント困るンだよ！　お金とか！<end_line>
  </sjis>
  <ascii>
    If you don't at least learn to<end_line>
    repair things, we'll really<end_line>
    be in trouble! Financially!<end_line>
  </ascii>
</dialogue>
<dialogue>
  <info box="left">
  <portrait_l entry="player" eye="happy" mouth="stressed">
  <sjis>
    うわ～<end_line>
    現実的だ～<end_line>
  </sjis>
  <ascii>
    Uwah~<end_line>
    This is too real~<end_line>
  </ascii> 
</dialogue>
<dialogue>
  <info box="right">
  <portrait_l entry="player" eye="happy" mouth="stressed">
  <portrait_r name="player">
  <sjis>
    きびしい現実がわかったら<end_line>
    少しでも修行しな！<end_line>
  </sjis>
  <ascii>
    It looks like you understand<end_line>
    our situation, so hurry it up!<end_line>
  </ascii>
</dialogue>
<dialogue>
  <info box="left">
  <portrait_l entry="player" eye="serious" mouth="neutral">
  <sjis>
    はい<end_line>
  </sjis>
  <ascii>
    Okay!<end_line>
  </ascii>
</dialogue>
<dialogue>
  <info box="right">
  <portrait_l entry="player" eye="serious" mouth="neutral">
  <portrait_r name="player">
  <sjis>
    <partner>も！<end_line>
  </sjis>
  <ascii>
    You too, <partner>!<end_line>
  </ascii>
</dialogue>
<dialogue>
  <partner name="run-dor">
  <info box="left">
  <portrait_l entry="partner" eye="serious" mouth="neutral">
  <sjis>
    <three_dots><end_line>
    了解デス<end_line>
  </sjis>
  <ascii>
    <three_dots><end_line>
    Roger.<end_line>
  </ascii>
</dialogue>
<dialogue>
  <partner name="enzi">
  <info box="left">
  <portrait_l entry="partner" eye="serious" mouth="tense">
  <sjis>
    仕方がないのぉ<three_dots><end_line>
  </sjis>
  <ascii>
    I'll concede for now<three_dots><end_line>
  </ascii>
</dialogue>
<dialogue>
  <partner name="killfith">
  <info box="left">
  <portrait_l entry="partner" eye="serious" mouth="neutral">
  <sjis>
    好きにしてくれ<three_dots><end_line>
  </sjis>
  <ascii>
    Fine<three_dots><end_line>
  </ascii>
</dialogue>
<dialogue>
  <partner name="rufeel">
  <info box="left">
  <portrait_l entry="partner" eye="serious" mouth="neutral">
  <sjis>
    わかりましたわ<end_line>
  </sjis>
  <ascii>
    I understand.<end_line>
  </ascii>
</dialogue>