<location>
  <sjis>
    マニグ採掘場<end_line>
  </sjis>
</location>
<location>
  <sjis>
    マニグ採掘場　エリア２<end_line>
  </sjis>
</location>
<popup>
  <sjis>
    元気になった！<end_line>
  </sjis>
  <ascii>
    Recovered!<end_line>
  </ascii>
</popup>
<dialogue>
  <info box="special">
  <sjis>
    回復ポイントでは、ＨＰと<end_line>
    魔法の使用回数を回復する<end_line>
    事ができます<end_line>
  </sjis>
  <ascii>
    At restoration points,<end_line>
    you can restore HP<end_line>
    and Magic uses.<end_line>
  </ascii>
</dialogue>
<dialogue>
  <info box="special">
  <sjis>
    回復ポイントの上に乗りＡボタンで<end_line>
    使用します<end_line>
  </sjis>
  <ascii>
    Use it by standing on<end_line>
    the point and pressing A.<end_line>
  </ascii>
</dialogue>
<dialogue>
  <info box="special">
  <sjis>
    一度回復すると使えなくなりますが<end_line>
    ダンジョンに入り直すことで<end_line>
    再び使用できる状態に戻ります<end_line>
  </sjis>
  <ascii>
    You can only use it once.<end_line>
    You may only use it again<end_line> 
	by re-entering the dungeon.<end_line>
  </ascii>
</dialogue>
