<location>
  <sjis>
    ディックル村<end_line>
  </sjis>
</location>
#Deckell Village
<location>
  <sjis>
    ディックル村　鉱洞入り口<end_line>
  </sjis>
</location>
#Deckell Village - Mine Entrance
<dialogue>
  <info box="simple">
  <portrait_l name="player">
  <sjis>
    ここは鉱山なんだけど<end_line>
    はぐれが強いから材料探しは<end_line>
    別の場所にしよう<end_line>
  </sjis>
  <ascii>
    A mine has plenty of materials<three_dots><end_line>
    But powerful Strays too.<end_line>
    Let's go somewhere else for now.<end_line>
  </ascii>
</dialogue>
<dialogue>
  <info box="simple">
  <portrait_l name="man">
  <sjis>
    ディックル鉱洞は今、立ち入り禁止だよ<end_line>
    この間の地震でいろんなとこが<end_line>
    くずれてて、あぶないんだ<end_line>
  </sjis>
  <ascii>
    Deckell Mine is off limits.<end_line>
    The earthquake caused parts of<end_line>
    the mine to cave in.<end_line>
  </ascii>
</dialogue>
<dialogue>
  <info box="simple">
  <sjis>
    みぃ～<end_line>
  </sjis>
  <ascii>
    Meow~<end_line>
  </ascii>
</dialogue>